{
  "exp_index": 3,
  "exp_total": 3,
  "exp_name": "Parameter-matched CNN accuracy-energy frontier",
  "exp_manifest": [
    [
      1,
      "DIAT ablation + dissociation [Tables 2,5]",
      "done"
    ],
    [
      2,
      "SHD speaker-disjoint ranking [Table 4]",
      "done"
    ],
    [
      3,
      "Parameter-matched CNN frontier [Table 3 / Fig 1]",
      "THIS"
    ]
  ],
  "split": "stratified seed=0 (3151/728/970)",
  "input": "plain (train-stat standardised)",
  "protocol": {
    "seeds": [
      42,
      123,
      999
    ],
    "batch": 128,
    "max_epochs": 200,
    "patience": 20,
    "val_smooth": 5,
    "lr": 0.001,
    "weight_decay": 0.0001,
    "optimizer": "Adam",
    "sched": "CosineAnnealingLR",
    "selection": "val-smoothed macro-F1"
  },
  "energy_model": {
    "E_MAC_pJ": 4.6,
    "E_AC_pJ": 0.9,
    "T": 64,
    "cnn_energy": "macs * E_MAC (dense)"
  },
  "snn_ref_locked": {
    "Doppler-LIF (tuned)": {
      "f1": 0.924,
      "params": 475000,
      "energy_uJ": 11.8
    },
    "Vanilla-LIF (tuned)": {
      "f1": 0.857,
      "params": 281000,
      "energy_uJ": 8.0
    },
    "Parametric-LIF (tuned)": {
      "f1": 0.852,
      "params": 283000,
      "energy_uJ": 8.0
    }
  },
  "frontier": [
    {
      "ch": [
        8,
        16,
        32
      ],
      "f1_mean": 0.9204193310628922,
      "f1_std": 0.028366152734511197,
      "acc_mean": 0.9219931271477663,
      "params": 6198,
      "macs": 2654400,
      "energy_uJ": 12.21024,
      "n_seeds": 3
    },
    {
      "ch": [
        16,
        32,
        64
      ],
      "f1_mean": 0.9232128725620536,
      "f1_std": 0.0207851661423943,
      "acc_mean": 0.9233676975945017,
      "params": 23910,
      "macs": 10027392,
      "energy_uJ": 46.1260032,
      "n_seeds": 3
    },
    {
      "ch": [
        32,
        64,
        128
      ],
      "f1_mean": 0.9212403489704698,
      "f1_std": 0.042542555002413024,
      "acc_mean": 0.9213058419243986,
      "params": 93894,
      "macs": 38929152,
      "energy_uJ": 179.07409919999998,
      "n_seeds": 3
    },
    {
      "ch": [
        48,
        96,
        192
      ],
      "f1_mean": 0.9692472333315889,
      "f1_std": 0.012104768591222087,
      "acc_mean": 0.9694158075601375,
      "params": 209958,
      "macs": 86705280,
      "energy_uJ": 398.84428799999995,
      "n_seeds": 3
    },
    {
      "ch": [
        64,
        128,
        256
      ],
      "f1_mean": 0.9477813861654055,
      "f1_std": 0.048270036888516,
      "acc_mean": 0.9467353951890035,
      "params": 372102,
      "macs": 153355776,
      "energy_uJ": 705.4365696,
      "n_seeds": 3
    },
    {
      "ch": [
        72,
        144,
        288
      ],
      "f1_mean": 0.974863515679029,
      "f1_std": 0.009210766286886276,
      "acc_mean": 0.9749140893470791,
      "params": 470454,
      "macs": 193758912,
      "energy_uJ": 891.2909952,
      "n_seeds": 3
    },
    {
      "ch": [
        80,
        160,
        320
      ],
      "f1_mean": 0.9840966088693063,
      "f1_std": 0.0005118609937968423,
      "acc_mean": 0.984192439862543,
      "params": 580326,
      "macs": 238880640,
      "energy_uJ": 1098.8509439999998,
      "n_seeds": 3
    }
  ],
  "ref_reproduction": {
    "ch": [
      16,
      32,
      64
    ],
    "f1_mean": 0.9232128725620536,
    "f1_std": 0.0207851661423943,
    "acc_mean": 0.9233676975945017,
    "params": 23910,
    "macs": 10027392,
    "energy_uJ": 46.1260032,
    "n_seeds": 3
  },
  "crux": {
    "snn_target_f1": 0.924,
    "snn_energy_uJ": 11.8,
    "cheapest_cnn_matching_acc": {
      "ch": [
        48,
        96,
        192
      ],
      "f1_mean": 0.9692472333315889,
      "f1_std": 0.012104768591222087,
      "acc_mean": 0.9694158075601375,
      "params": 209958,
      "macs": 86705280,
      "energy_uJ": 398.84428799999995,
      "n_seeds": 3
    },
    "best_cnn_within_budget": null,
    "verdict": "HOLDS",
    "note": "SNN reaches 0.924 at 11.8 uJ; the cheapest CNN matching it costs 398.8 uJ (33.8x more)."
  },
  "timestamp": "2026-06-18T20:08:56.547738"
}